sqlrepl/__init__.py
sqlrepl/cmd.py
sqlrepl/repl.py
sqlrepl/settings.py
sqlalchemy_repl-0.1.0.dist-info/METADATA
sqlalchemy_repl-0.1.0.dist-info/WHEEL
sqlalchemy_repl-0.1.0.dist-info/RECORD
